{
  "kind": "singleType",
  "collectionName": "transparencia_decreto_unico",
  "info": {
    "singularName": "transparencia-decreto-unico",
    "pluralName": "transparencia-decreto-unicos",
    "displayName": "06. Transparencia / Decreto Unico",
    "description": "Página única del dominio \"Transparencia\": Decreto Unico. Publicada en: /decreto-unico-reglamentario. Edite estos campos para actualizar el contenido que ven los visitantes del sitio.",
    "mainField": "title"
  },
  "options": {
    "draftAndPublish": true
  },
  "pluginOptions": {},
  "attributes": {
    "title": {
      "type": "string"
    },
    "description": {
      "type": "string"
    },
    "icon": {
      "type": "string"
    },
    "documentos": {
      "type": "component",
      "component": "transparencia-decreto-unico.documento",
      "repeatable": true
    }
  }
}
